pcce/__init__.py
pcce/_version.py
pcce/agentless.py
pcce/application_control.py
pcce/audits.py
pcce/authenticate.py
pcce/authenticate_client.py
pcce/certs.py
pcce/cloud.py
pcce/coderepos_ci.py
pcce/collections.py
pcce/containers.py
pcce/credentials.py
pcce/current.py
pcce/custom_compliance.py
pcce/custom_rules.py
pcce/defenders.py
pcce/feeds.py
pcce/groups.py
pcce/hosts.py
pcce/images.py
pcce/pcce.py
pcce/ping.py
pcce/policies.py
pcce/profiles.py
pcce/registry.py
pcce/sandbox.py
pcce/scans.py
pcce/serverless.py
pcce/settings.py
pcce/signup.py
pcce/stats.py
pcce/statuses.py
pcce/tags.py
pcce/tas_droplets.py
pcce/trust.py
pcce/users.py
pcce/util.py
pcce/version.py
pcce/vms.py
pcce/waas.py
pcce/schema/__init__.py
pcce/schema/agentless.py
pcce/schema/application_control.py
pcce/schema/audits.py
pcce/schema/cloud.py
pcce/schema/coderepos_ci.py
pcce/schema/collections.py
pcce/schema/containers.py
pcce/schema/credentials.py
pcce/schema/custom_compliance.py
pcce/schema/custom_rules.py
pcce/schema/defenders.py
pcce/schema/feeds.py
pcce/schema/groups.py
pcce/schema/hosts.py
pcce/schema/images.py
pcce/schema/policies.py
pcce/schema/profiles.py
pcce/schema/registry.py
pcce/schema/sandbox.py
pcce/schema/scans.py
pcce/schema/serverless.py
pcce/schema/settings.py
pcce/schema/stats.py
pcce/schema/tags.py
pcce/schema/tas_droplets.py
pcce/schema/trust.py
pcce/schema/users.py
pcce/schema/utils.py
pcce/schema/vms.py
pcce/utils/__init__.py
pcce/utils/file.py
pcce_api-1.0rc1.dist-info/WHEEL
pcce_api-1.0rc1.dist-info/METADATA
pcce_api-1.0rc1.dist-info/RECORD
