Metadata-Version: 2.1
Name: pcce-api
Version: 1.0rc1
Summary: Prisma Cloud Compute Edition API Client
Keywords: Prisma Cloud,Prisma Cloud Compute,Palo Alto,CNAPP,API
Author-email: Pham Xuan Quynh <th1nks1mple@protonmail.com>
Maintainer-email: Pham Xuan Quynh <th1nks1mple@protonmail.com>
Requires-Python: >=3.8.1
Classifier: Development Status :: 4 - Beta
Classifier: Intended Audience :: Developers
Classifier: Topic :: Security
Classifier: License :: OSI Approved :: MIT License
Classifier: Programming Language :: Python :: 3 :: Only
Classifier: Programming Language :: Python :: 3.8
Classifier: Programming Language :: Python :: 3.9
Classifier: Programming Language :: Python :: 3.10
Classifier: Programming Language :: Python :: 3.11
Classifier: Programming Language :: Python :: 3.12
Requires-Dist: marshmallow>=3.21.3
Requires-Dist: requests>=2.31.0
Requires-Dist: restfly>=1.4.7
Requires-Dist: black==24.3.0 ; extra == "test"
Requires-Dist: bandit[toml]==1.7.9 ; extra == "test"
Requires-Dist: flake8 ; extra == "test"
Requires-Dist: flake8-docstrings ; extra == "test"
Requires-Dist: flake8-bugbear==23.5.9 ; extra == "test"
Requires-Dist: flake8-pyproject ; extra == "test"
Requires-Dist: pre-commit==3.3.1 ; extra == "test"
Requires-Dist: pylint==2.17.4 ; extra == "test"
Requires-Dist: pytest==7.3.1 ; extra == "test"
Requires-Dist: responses==0.25.3 ; extra == "test"
Requires-Dist: pytest-cov==4.0.0 ; extra == "test"
Requires-Dist: tomli==2.0.1 ; extra == "test"
Project-URL: Documentation, https://gitlab.com/th1nks1mple/pcce-api
Project-URL: Source, https://gitlab.com/th1nks1mple/pcce-api
Project-URL: Tracker, https://gitlab.com/th1nks1mple/pcce-api/-/issues
Provides-Extra: test
